keras_geometric/__init__.py
keras_geometric/_version.py
keras_geometric/datasets/__init__.py
keras_geometric/datasets/base.py
keras_geometric/datasets/citation.py
keras_geometric/datasets/cora.py
keras_geometric/layers/__init__.py
keras_geometric/layers/aggregators.py
keras_geometric/layers/gatv2_conv.py
keras_geometric/layers/gcn_conv.py
keras_geometric/layers/gin_conv.py
keras_geometric/layers/message_passing.py
keras_geometric/layers/sage_conv.py
keras_geometric/layers/pooling/__init__.py
keras_geometric/layers/pooling/attention_pooling.py
keras_geometric/layers/pooling/global_pooling.py
keras_geometric/utils/__init__.py
keras_geometric/utils/data_utils.py
keras_geometric/utils/main.py
keras_geometric-0.0.2.dist-info/METADATA
keras_geometric-0.0.2.dist-info/WHEEL
keras_geometric-0.0.2.dist-info/licenses/LICENSE
keras_geometric-0.0.2.dist-info/RECORD
