Metadata-Version: 2.4
Name: keras-geometric
Version: 0.0.2
Summary: A Python package for building and training graph neural networks using Keras.
Project-URL: Homepage, https://github.com/Huvinesh-Rajendran-12/keras-geometric
Project-URL: Repository, https://github.com/Huvinesh-Rajendran-12/keras-geometric
Author-email: Huvinesh <huvineshrajendran@gmail.com>
License: MIT License
License-File: LICENSE
Keywords: gcn,geometric,gin,gnn,graph neural network,keras
Classifier: Development Status :: 3 - Alpha
Classifier: Intended Audience :: Developers
Classifier: Intended Audience :: Science/Research
Classifier: License :: OSI Approved :: MIT License
Classifier: Programming Language :: Python :: 3
Classifier: Programming Language :: Python :: 3.9
Classifier: Programming Language :: Python :: 3.10
Classifier: Programming Language :: Python :: 3.11
Classifier: Programming Language :: Python :: 3.12
Classifier: Topic :: Scientific/Engineering :: Artificial Intelligence
Classifier: Topic :: Software Development :: Libraries :: Python Modules
Requires-Python: >=3.9
Requires-Dist: jax[cpu]>=0.4.30
Requires-Dist: jaxlib>=0.4.30
Requires-Dist: keras>=3.0
Requires-Dist: numpy>=1.24.0
Requires-Dist: pytest>=8.3.5
Requires-Dist: tensorflow>=2.19.0
Requires-Dist: torch>=2.6.0
Provides-Extra: all
Requires-Dist: psutil>=5.9.0; extra == 'all'
Requires-Dist: pytest>=8.3.5; extra == 'all'
Requires-Dist: scipy>=1.11.0; extra == 'all'
Requires-Dist: tensorflow-metal>=1.2.0; (platform_system == 'Darwin' and platform_machine == 'arm64') and extra == 'all'
Requires-Dist: tensorflow>=2.17; extra == 'all'
Requires-Dist: torch-geometric>=2.6.1; extra == 'all'
Requires-Dist: torch>=2.6.0; extra == 'all'
Provides-Extra: datasets
Requires-Dist: scipy>=1.11.0; extra == 'datasets'
Provides-Extra: dev
Requires-Dist: build>=1.0.0; extra == 'dev'
Requires-Dist: hatch>=1.12.0; extra == 'dev'
Requires-Dist: pip-audit>=2.7.0; extra == 'dev'
Requires-Dist: pre-commit>=4.2.0; extra == 'dev'
Requires-Dist: psutil>=5.9.0; extra == 'dev'
Requires-Dist: pyrefly; extra == 'dev'
Requires-Dist: pytest>=8.3.5; extra == 'dev'
Requires-Dist: ruff>=0.8.0; extra == 'dev'
Requires-Dist: safety>=3.0.0; extra == 'dev'
Requires-Dist: scipy>=1.11.0; extra == 'dev'
Requires-Dist: tensorflow>=2.17; extra == 'dev'
Requires-Dist: torch-geometric>=2.6.1; extra == 'dev'
Requires-Dist: torch>=2.6.0; extra == 'dev'
Requires-Dist: twine>=5.0.0; extra == 'dev'
Provides-Extra: macos-metal
Requires-Dist: tensorflow-metal>=1.2.0; (platform_system == 'Darwin' and platform_machine == 'arm64') and extra == 'macos-metal'
Provides-Extra: test
Requires-Dist: psutil>=5.9.0; extra == 'test'
Requires-Dist: pytest>=8.3.5; extra == 'test'
Requires-Dist: scipy>=1.11.0; extra == 'test'
Requires-Dist: tensorflow>=2.17; extra == 'test'
Requires-Dist: torch-geometric>=2.6.1; extra == 'test'
Requires-Dist: torch>=2.6.0; extra == 'test'
